{
  "row_number": 20260428,
  "sr.no": 20260428,
  "id": 20260428,
  "title": "Angel Number 555: Decoding the Divine Signal for Major Life Changes",
  "slug": "angel-number-555-major-life-changes",
  "excerpt": "Is 555 appearing everywhere? Discover the profound numerological significance of Angel Number 555 and how it signals a transformative shift in your life journey.",
  "category": "Numerology",
  "date": "May 12, 2026",
  "readTime": "15 min",
  "image_name": "angel-number-555-transformation.png",
  "image_prompt": "A high-end, cinematic mystical scene featuring a glowing triple 5 formation floating in a dark ethereal void. The palette is dominated by deep indigo, royal violet, and shimmering gold particles. The atmosphere is dense with cosmic dust and ancient geometric patterns, creating a sense of profound spiritual awakening and major life transition. 8k resolution, photorealistic, mystical lighting.",
  "image": "/blog-images/angel-number-555-transformation.png",
  "content": "<h2>The Mystical Significance of Angel Number 555</h2><p>In the vast realm of numerology, few sequences carry the electric, transformative vibration of <b>Angel Number 555</b>. When this numerical triad begins to manifest in your daily life—on clocks, receipts, license plates, or phone numbers—it is rarely a mere coincidence. It is an intentional, cosmic nudge from the universe signaling that you are standing on the precipice of a profound life cycle shift.</p><p>The number 5 is inherently associated with the planet Mercury in Vedic astrology, representing intellect, communication, curiosity, and adaptability. When tripled, this energy is amplified exponentially. It signifies that the stagnant waters of your current reality are about to be stirred, paving the way for fresh opportunities that align with your higher soul purpose.</p><p>For those seeking guidance, <b>Angel Number 555</b> acts as a spiritual harbinger. It suggests that the obstacles you have faced in the past were merely lessons intended to sharpen your resilience. Now, the universe is providing the keys to unlock a newer, more authentic version of yourself. This is not a time for fear, but a time for intentional preparation.</p><h3>Understanding the Vibration of Five</h3><p>The core essence of the number 5 is movement. It represents the five senses, the five elements, and the five extremities of the human body. In <b>NumGuru</b> philosophy, we view this as the number of the 'Explorer.' It craves freedom, thrives on change, and possesses an inherent desire to break free from the shackles of convention.</p><p>When you see 555, the universe is telling you that the 'status quo' is no longer serving your evolution. You might have felt an internal restlessness or a deep-seated need to move, change careers, or alter your relationships. This is the vibration of the 5 manifesting in your psyche, urging you to embrace the flow of life rather than resisting it.</p><p>Furthermore, 5 is the midpoint between 1 and 9, making it a pivotal bridge. It represents the transition from the initiation phase to the completion phase of your karmic journey. This numerical frequency demands that you remain adaptable and open-minded, as the changes arriving may not look like what you expected, but they are exactly what your soul requires.</p><h3>The Connection to Vedic Numerology</h3><p>While Western numerology focuses heavily on Angelic guidance, our Indian <b>Vedic Numerology</b> perspective looks at the underlying planetary influences. In our system, the number 5 is ruled by Budh (Mercury). This planet governs our analytical capabilities and our communication with the divine.</p><p>When 555 appears, it indicates that your mental faculties are being sharpened by cosmic forces. It is a period where your intuition will be at its peak. If you have been struggling to make a decision, this is a sign that the fog is clearing. The universe is aligning your cognitive powers with the wisdom of your heart.</p><p>We must also consider the sum of 5+5+5, which equals 15, and 1+5 equals 6. In numerology, 6 is the number of harmony, family, and domestic balance. Thus, 555 serves as a catalyst for change that ultimately leads to a more harmonious life. The disruption you may experience initially is simply the clearing of space for long-term stability.</p><h2>Calculating Your Personal Numerological Influence</h2><p>To truly understand how <b>Angel Number 555</b> impacts your life, you must first understand your personal foundation. At NumGuru, we emphasize the importance of the <b>Driver and Conductor numbers</b>. These are calculated based on your date of birth and dictate your inherent personality and your life’s destiny.</p><p>Your Driver number represents your basic personality, how you perceive the world, and your initial reactions to life events. Your Conductor (or Destiny) number represents the long-term path you are meant to walk and the lessons you are meant to master. Knowing these allows you to see how the energy of 555 interacts with your unique blueprint.</p><h3>Step-by-Step: Finding Your Driver Number</h3><p>The Driver number is simple to calculate. Take your day of birth and reduce it to a single digit. For example, if you were born on the 23rd, your Driver number is 2 + 3 = 5. Interestingly, if your Driver number is 5, seeing 555 is a direct resonance with your soul's core frequency.</p><p>If you were born on the 9th, your Driver number is 9. If you were born on the 10th, it is 1 + 0 = 1. This number dictates your approach to change. A person with a Driver number 5 will embrace the energy of 555 with excitement, whereas a person with a Driver number 4 (a number of structure) might find the sudden change brought by 555 initially unsettling.</p><p>By understanding your Driver number, you can better manage the transition that 555 brings. It helps you identify your emotional baseline and prepares you to handle the volatility of the changes with grace and poise rather than panic.</p><h3>Step-by-Step: Finding Your Conductor Number</h3><p>The Conductor number is calculated by adding every single digit of your full date of birth (Day + Month + Year) until you arrive at a single digit. Let us use the example of someone born on 15th October 1990 (15-10-1990).</p><p>Calculation: 1+5 (Day) = 6. 1+0 (Month) = 1. 1+9+9+0 (Year) = 19; 1+9 = 10; 1+0 = 1. Now, add the results: 6 + 1 + 1 = 8. In this case, the Conductor number is 8. This person is likely to experience the changes of 555 as a significant shift in their career or financial standing.</p><p>When 555 appears, look at your Conductor number to see which area of life will be most affected. If your Conductor is 1, expect changes in leadership roles. If it is 2, expect changes in relationships. If it is 5, expect a total life overhaul. This systematic approach is what makes NumGuru insights so precise and actionable for our community.</p><h2>The Various Facets of Change</h2><p>Change is often perceived as a negative experience by the ego, which craves safety and predictability. However, <b>Angel Number 555</b> is a spiritual message that change is the only constant. It is the universe’s way of ensuring you do not become stagnant in your spiritual or material development.</p><p>There are different types of changes that 555 may herald. Some are internal, involving a shift in perspective or a shedding of old beliefs. Others are external, such as moving to a new city, starting a new business venture, or ending a toxic relationship. Regardless of the form it takes, the message remains the same: trust the process.</p><h3>Internal Shifts and Soul Growth</h3><p>Often, 555 is a sign of a massive <b>spiritual awakening</b>. You might find yourself suddenly interested in topics you previously ignored, such as meditation, energy healing, or sacred geometry. This is your soul waking up from the slumber of everyday life, demanding to be fed with higher knowledge.</p><p>During this phase, you may feel detached from friends or hobbies that you once loved. Do not fear this isolation; it is a necessary period of introspection. The 555 energy is clearing out the cobwebs of your past so that you can align with your true purpose. Embrace this silence, as it is in the silence that the universe speaks the loudest.</p><p>Your intuition will become incredibly sharp. You may experience synchronicities that seem impossible. These are not coincidences; they are breadcrumbs left by your guides to lead you to your next chapter. Trust your gut feelings during this time, even if they contradict logic, as your higher self is guiding the ship.</p><h3>External Transformations and Career Shifts</h3><p>In the material world, 555 often signals the end of a career phase. If you have been feeling unfulfilled in your job, this is the cosmic green light to look for something that aligns with your passions. The number 5 is associated with business, communication, and networking, making it an excellent time to pivot your professional life.</p><p>If you have been contemplating an entrepreneurial journey, the appearance of 555 is a powerful omen of success. It suggests that you have the intellectual capability and the adaptability to handle the challenges of starting a business. However, it also demands that you remain flexible—be prepared to change your strategy if the market demands it.</p><p>Financial changes are also common when 555 manifests. This could mean a sudden increase in income, an unexpected expense that forces you to change your habits, or a shift in how you view money. Regardless, it is a call to take control of your financial destiny and stop relying on outdated methods of wealth management.</p><h2>How to Align with the Energy of 555</h2><p>Seeing the number 555 is an invitation to participate in the change rather than being a victim of it. To harness this power effectively, you must adopt a mindset of <b>intentional surrender</b>. This means releasing control over the 'how' and 'when,' while remaining deeply committed to your goal.</p><p>Many people struggle when they see this number because they try to force outcomes. If you are going through a transition, trying to micromanage every detail will only lead to stress. Instead, focus on your vibration. Keep your thoughts positive and your actions aligned with your highest values.</p><p>Use this time to perform daily gratitude rituals. Gratitude is the highest form of frequency. By being thankful for the changes, even the difficult ones, you signal to the universe that you are ready for more growth. This mindset shift is the key to unlocking the true potential of the 555 energy.</p><h3>Meditation and Visualization</h3><p>When you frequently encounter 555, dedicate time to quiet meditation. Sit in a comfortable position, close your eyes, and visualize the number 555 in front of you. Imagine its golden light enveloping your body, clearing away any fear or resistance to change.</p><p>Ask yourself, 'What needs to change in my life for me to feel more aligned?' The answer will often surface during these quiet moments. Once you have identified the area, visualize yourself moving through that change with ease and grace. See yourself successfully adapting to the new circumstances.</p><p>Consistency is key. Do this practice for 5 minutes every day until you feel a sense of inner peace regarding the upcoming changes. This practice helps to stabilize the volatile energy of 5 and turns it into a productive force for your personal development.</p><h3>The Power of Affirmations</h3><p>Affirmations are a tool to reprogram the subconscious mind, which is essential when the universe is pushing you toward change. When you see 555, repeat phrases like: 'I embrace change with an open heart,' 'I am ready for the new opportunities coming my way,' and 'The universe is guiding me toward my highest good.'</p><p>These words act as an anchor. When the winds of change start blowing hard, your affirmations will remind you that you are not being destroyed, but built anew. Repeat these in front of a mirror, looking yourself in the eye, to truly integrate the belief into your spirit.</p><p>Combined with the energy of 555, these affirmations become potent incantations. They align your vibration with the frequency of abundance and growth, ensuring that the changes you experience are positive and long-lasting.</p><h2>Overcoming the Fear of the Unknown</h2><p>The greatest hurdle when facing <b>major life changes</b> is fear. The human ego is hardwired to seek comfort and safety. When 555 enters your life, it disrupts that safety. It is natural to feel anxious, but it is vital to remember that the universe does not give us challenges we are not equipped to handle.</p><p>In Vedic philosophy, we believe that every soul has a specific destiny. Sometimes, the universe forces us to change because we have outgrown our current path. If we refuse to move, we become blocked, and life becomes heavy. Change is, in essence, a form of spiritual liberation.</p><p>When fear arises, ground yourself. Use crystals like Black Tourmaline or Hematite, or walk barefoot on the earth. These practices help to stabilize your base chakra (Muladhara), ensuring that even as your life changes, your foundation remains secure.</p><h3>Why Resistance Creates Suffering</h3><p>Resistance is the root cause of most human suffering. When the universe signals a change through 555, and you fight it, you create internal friction. This friction manifests as stress, illness, or repetitive negative patterns. The more you fight, the harder the universe will push, because your growth is non-negotiable.</p><p>Instead of resisting, practice 'flow.' Imagine yourself as a river. A river flows around rocks and obstacles, never stopping, never fighting, simply moving toward the ocean. You are that river. The obstacles are the changes brought by 555. Flow around them, learn from them, and continue your journey.</p><p>Acceptance does not mean you like the change immediately. It means you acknowledge that the change is happening and you choose to respond with wisdom rather than reaction. This is the hallmark of a spiritually mature individual.</p><h3>Trusting the Divine Timing</h3><p>Everything in the cosmos operates on divine timing. <b>Angel Number 555</b> is proof that you are exactly where you need to be. If you feel like things are moving too fast, trust that the speed is necessary. If you feel like things are moving too slow, trust the delay is for your protection.</p><p>The universe has a bird’s-eye view of your life that you do not possess. What looks like a disaster from your perspective might be the very thing that prevents a future catastrophe or opens a door to a massive blessing. Trust in the grand design of your life.</p><p>By letting go of your need to control the timeline, you open yourself up to synchronicities that make the journey much smoother. Keep your eyes open for signs, listen to your inner voice, and move forward with the faith that you are being supported by the divine.</p><h2>The Role of Karma in Your Transformation</h2><p>In the context of <b>NumGuru</b>, we cannot discuss life changes without addressing the laws of Karma. Every action you take, every thought you nurture, and every choice you make creates a karmic footprint. 555 often appears when you are clearing old karmic debts.</p><p>You might be wondering why you are dealing with specific issues at this time. Often, it is because your soul is ready to balance these accounts. The changes you are going through are the universe's way of balancing your energetic ledger, allowing you to move into a cleaner, more vibrant karmic space.</p><h3>Clearing Karmic Debt</h3><p>If you have been holding onto past regrets, anger, or guilt, the energy of 555 will likely bring these to the surface. Do not be alarmed. This is not to punish you, but to help you release them. You cannot enter a new phase of your life carrying the heavy baggage of your past.</p><p>Forgiveness is the most powerful tool for clearing karmic debt. Forgive yourself for past mistakes and forgive others for their roles in your journey. Once you release these attachments, you will find that the changes signaled by 555 become much easier to navigate.</p><p>View your past experiences as 'classroom lessons.' Once you have learned the lesson, there is no need to repeat the grade. By acknowledging the lesson, you transmute the karma and clear the way for your future to unfold in alignment with your highest potential.</p><h3>Creating Positive Future Karma</h3><p>As you transition through the changes indicated by 555, focus on creating positive future karma. This means acting with integrity, kindness, and mindfulness. Every choice you make during this period of transition has a ripple effect that will influence your future years.</p><p>Be mindful of your intentions. Are you making changes to please others, or to honor your own soul? If the latter, you are creating excellent karma. When your actions are aligned with your authentic self, the universe rewards you with further opportunities and blessings.</p><p>Your current transformation is the seed of your future reality. Plant that seed with care, water it with positivity, and nurture it with consistent, mindful action. The results will manifest in your life as greater success, deeper relationships, and a profound sense of inner peace.</p><h2>NumGuru: Your Partner in Spiritual Navigation</h2><p>Numerology is more than just a sequence of numbers; it is a profound map of your soul's journey. At <b>NumGuru</b>, we believe that everyone has the right to understand their own cosmic blueprint. By decoding the numbers that surround you, you gain a level of self-awareness that is both empowering and transformative.</p><p>Whether you are encountering 555 or any other sequence, our platform is designed to provide you with the insights you need to make sense of your experiences. We combine ancient Vedic wisdom with modern analytical techniques to offer you a personalized look at your life path.</p><p>Don't just watch the signs—understand them. When you have the knowledge, you move from being a passenger in your own life to being the driver. Our platform provides the tools to help you navigate the complexities of life with confidence and clarity.</p><h3>Why Personalized Numerology Matters</h3><p>General horoscopes and generic numerology readings can only take you so far. Your life is unique, dictated by the exact moment you entered this world. A personalized audit takes into account your specific date of birth and your name, providing a level of detail that generic readings simply cannot match.</p><p>At <b>NumGuru</b>, we analyze the interplay between your Driver and Conductor numbers, your soul urge, and your karmic cycles. This gives you a comprehensive view of your strengths, weaknesses, and the cycles of change you are currently moving through. It is the ultimate roadmap for your soul.</p><p>Understanding your personal numbers allows you to make informed decisions. You will know when to take risks, when to wait, and when to act. This is the power of numerology—it removes the guesswork and replaces it with divine guidance.</p><hr><h2>Unlock Your Personalized 20+ Page Numerology Audit</h2><p>Are you ready to stop guessing and start living in alignment with your true destiny? The numbers 555 are just the beginning of your conversation with the universe. At <b>NumGuru</b>, we offer a comprehensive 20+ page <b>Personalized Numerology Audit</b> that dives deep into your soul’s blueprint.</p><p>By entering your Name and Date of Birth into our advanced <b>NumGuru Calculator</b>, you will receive a detailed analysis that includes: <ul><li>Your primary <b>Driver and Conductor Numbers</b> and their specific influence on your life.</li><li>A deep dive into your <b>Soul Urge</b>, revealing what truly drives your heart’s desires.</li><li>An exploration of your <b>Karmic Laws</b> and how they are shaping your current reality.</li><li>A guide to your <b>Lucky Colors</b>, numbers, and days to optimize your daily vibration.</li><li>Insights into your <b>Personal Year cycle</b> to help you plan your future with precision.</li></ul></p><p>Do not let the wisdom of the numbers pass you by. Take the step today to unlock your potential and gain the clarity you deserve. Visit the <b>NumGuru</b> website now and embark on the journey of a lifetime. Your future self will thank you.</p>",
  "status": "ready",
  "commit": ""
}